{
  "timestamp": "2026-02-08T02:34:00Z",
  "deployment_steps": [
    {
      "duration_s": 2,
      "step": "validate_module",
      "status": "passed"
    },
    {
      "duration_s": 1,
      "step": "backup_existing",
      "status": "passed"
    },
    {
      "duration_s": 5,
      "step": "deploy_module",
      "status": "success"
    },
    {
      "duration_s": 3,
      "step": "verify_deployment",
      "status": "passed"
    }
  ],
  "deployment_id": "DEPLOY-PH0-20260208",
  "performance": {
    "hash_operation_ms": 0.15,
    "baseline_target_ms": 500
  },
  "status": "success",
  "target": "production",
  "tests_passed": [
    "hash determinism",
    "UTF-8 encoding",
    "64-char output"
  ],
  "module": "canonical_hash"
}
